sretoolbox/__init__.py
sretoolbox/py.typed
sretoolbox/binaries/__init__.py
sretoolbox/binaries/base.py
sretoolbox/binaries/kubectl_package.py
sretoolbox/binaries/mtcli.py
sretoolbox/binaries/oc.py
sretoolbox/binaries/operator_sdk.py
sretoolbox/binaries/opm.py
sretoolbox/container/__init__.py
sretoolbox/container/image.py
sretoolbox/container/skopeo.py
sretoolbox/utils/__init__.py
sretoolbox/utils/concurrent.py
sretoolbox/utils/datatransformation.py
sretoolbox/utils/exception.py
sretoolbox/utils/k8s.py
sretoolbox/utils/logger.py
sretoolbox/utils/multiprocess.py
sretoolbox/utils/process.py
sretoolbox/utils/retry.py
sretoolbox/utils/threaded.py
sretoolbox-3.2.0.dist-info/METADATA
sretoolbox-3.2.0.dist-info/WHEEL
sretoolbox-3.2.0.dist-info/licenses/LICENSE
sretoolbox-3.2.0.dist-info/RECORD
