Metadata-Version: 2.4
Name: sretoolbox
Version: 3.2.0
Summary: Set of libraries commonly used by multiple SRE projects
Project-URL: homepage, https://github.com/app-sre/sretoolbox
Project-URL: repository, https://github.com/app-sre/sretoolbox
Project-URL: documentation, https://github.com/app-sre/sretoolbox
Author-email: Red Hat Application SRE Team <sd-app-sre@redhat.com>
License: Apache 2.0
License-File: LICENSE
Requires-Python: >=3.10
Requires-Dist: python-json-logger>=3.3.0
Requires-Dist: requests>=2.32.0
Requires-Dist: semver>=3.0.4
